{"FEATURE_ID":"RWG045181","SVDATE":"2017-07-12","PRK_CARR":false,"PRK_COVER":false,"PRK_SECURE":false,"PRK_LOCKER":false,"PRK_SHEFF":false,"PRK_MSTAND":false,"PRK_PSTAND":false,"PRK_HOOP":true,"PRK_POST":false,"PRK_BUTERF":false,"PRK_WHEEL":false,"PRK_HANGAR":false,"PRK_TIER":false,"PRK_OTHER":false,"PRK_PROVIS":1,"PRK_CPT":2,"BOROUGH":"Kensington & Chelsea","PHOTO1_URL":"https://cycleassetimages.data.tfl.gov.uk/RWG045181_1.jpg","PHOTO2_URL":"https://cycleassetimages.data.tfl.gov.uk/RWG045181_2.jpg","coordinates":[51.5086181221,-0.1952225493]}