{"FEATURE_ID":"RWG108482","SVDATE":"2017-06-30","PRK_CARR":true,"PRK_COVER":false,"PRK_SECURE":false,"PRK_LOCKER":false,"PRK_SHEFF":true,"PRK_MSTAND":false,"PRK_PSTAND":false,"PRK_HOOP":false,"PRK_POST":false,"PRK_BUTERF":false,"PRK_WHEEL":false,"PRK_HANGAR":false,"PRK_TIER":false,"PRK_OTHER":false,"PRK_PROVIS":8,"PRK_CPT":16,"BOROUGH":"City of London","PHOTO1_URL":"https://cycleassetimages.data.tfl.gov.uk/RWG108482_1.jpg","PHOTO2_URL":"https://cycleassetimages.data.tfl.gov.uk/RWG108482_2.jpg","coordinates":[51.5176175445,-0.1090370085]}