{"FEATURE_ID":"RWG156545","SVDATE":"2017-10-10","PRK_CARR":false,"PRK_COVER":false,"PRK_SECURE":false,"PRK_LOCKER":false,"PRK_SHEFF":true,"PRK_MSTAND":false,"PRK_PSTAND":false,"PRK_HOOP":false,"PRK_POST":false,"PRK_BUTERF":false,"PRK_WHEEL":false,"PRK_HANGAR":false,"PRK_TIER":false,"PRK_OTHER":false,"PRK_PROVIS":2,"PRK_CPT":4,"BOROUGH":"Havering","PHOTO1_URL":"https://cycleassetimages.data.tfl.gov.uk/RWG156545_1.jpg","PHOTO2_URL":"https://cycleassetimages.data.tfl.gov.uk/RWG156545_2.jpg","coordinates":[51.5990471848,0.1628648618]}